{
  "database": {
    "host": "rethinkdb-staging6110.cloudapp.net",
    "port": 28015,
    "db": "swipes",
    "user": "admin",
    "password": ""
  },
  "xendo": {
    "clientId": "99965e447026eb281dfc",
    "clientSecret": "2ffed44df0b40c81845780baa74ba57cc0a6f06c",
    "accessTokenEndpoint": "https://xen.do/oauth2/access_token",
    "addUserEndpoint": "https://xen.do/api/v1/provisioning/user/",
    "addServiceToUserEndpoint": "https://xen.do/api/v1/provisioning/service/",
    "searchEndpoint": "https://xen.do/api/v1/search/",
    "userServiceEndpoint": "https://xen.do/api/v1/user-service/"
  },
  "dropbox": {
    "appId": "qhkw8akehpocer3",
    "appSecret": "gjocjcvalr8xena",
    "redirectURI": "http://localhost:3000/oauth-success.html"
  },
  "asana": {
    "clientId": "93722876544112",
    "clientSecret": "07cf42d4b1190acb4333d66229fb080b",
    "redirectUri": "https://staging.swipesapp.com/oauth-success.html"
  },
  "slack": {
    "clientId": "2345135970.9201204242",
    "clientSecret": "306fd7099a762968aa876d53579fa694",
    "redirectUri": "http://localhost:3000/oauth-success.html"
  },
  "google": {
    "clientId": "336134475796-pab4vabvhf37tkkh82vi846e6jheq76i.apps.googleusercontent.com",
    "clientSecret": "KittPpq9liOYxktfVptv_kYr",
    "redirectUri": "http://localhost:3000/oauth-success.html"
  },
  "jira": {
    "authUrl": "http://localhost:3000/jira-auth.html",
    "redirectUri": "http://localhost:3000/oauth-success.html"
  },
  "amazonQueue": {
    "accessKeyId": "AKIAJYHNP3XSVYNJK7OA",
    "secretAccessKey": "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",
    "queueHost": "https://sqs.us-west-2.amazonaws.com/745159268654/Swipes.fifo"
  },
  "loggly": {
    "token": "a760d2ee-d576-466b-a8ff-53826455a13d",
    "tags": "swipesapp-staging-nodejs-errors",
    "subdomain": "swipesapp"
  },
  "valjs_debug": true,
  "origin": "http://localhost",
  "webhooksHost": "https://swipesdev.ngrok.io/",
  "apiPort": 5000,
  "clientPort" :3000,
  "protocol": "http://",
  "cors": "*",
  "jwtTokenSecret": "swipy the dinocat",
  "env": "dev"
}
